[
  {
    "name": "Plumbtastic Plumbing / Potty Doctor",
    "rating": 5,
    "reviews": 109,
    "phone": "(561) 203-5549",
    "website": "https://www.plumbtasticplumbing.com/",
    "address": "10524 Marsh St, Wellington, FL 33414, USA",
    "place_id": "ChIJfRtt9H8v2YgRUTsgAKXdscY",
    "maps_url": "https://maps.google.com/?cid=14317468391128972113"
  },
  {
    "name": "Smart Choice Plumbing & Air Conditioning LLC",
    "rating": 4.9,
    "reviews": 134,
    "phone": "(561) 629-5965",
    "website": "https://smartchoiceplumbingandairconditioning.com/",
    "address": "12510 Teakwood Ct, Wellington, FL 33414, USA",
    "place_id": "ChIJRXTSrJAv2YgRAbPv7793xHE",
    "maps_url": "https://maps.google.com/?cid=8197808887969067777"
  },
  {
    "name": "Mike The Plumber Inc",
    "rating": 4.9,
    "reviews": 149,
    "phone": "(561) 460-5017",
    "website": "https://miketheplumberinc.com/",
    "address": "8730 Arrowhead Dr A, Wellington, FL 33467, USA",
    "place_id": "ChIJVVVZWwgm2YgRDikCsw-xVqk",
    "maps_url": "https://maps.google.com/?cid=12202134921392826638"
  },
  {
    "name": "Davies Plumbing Services",
    "rating": 5,
    "reviews": 196,
    "phone": "(561) 707-6884",
    "website": "http://desllc.co/",
    "address": "8315 Rodeo Dr, Wellington, FL 33467, USA",
    "place_id": "ChIJTYMJeg4m2YgRRTwJbcxyEAc",
    "maps_url": "https://maps.google.com/?cid=509032980221082693"
  },
  {
    "name": "Go To Plumber",
    "rating": 5,
    "reviews": 179,
    "phone": "(561) 379-1324",
    "website": "http://www.gotoplumberco.com/",
    "address": "342 Pike Rd, West Palm Beach, FL 33411, USA",
    "place_id": "ChIJy9jqmArcr2YRS_lE3Pq8wx8",
    "maps_url": "https://maps.google.com/?cid=2288880821257697611"
  },
  {
    "name": "Copperhead Plumbing LLC",
    "rating": 4.9,
    "reviews": 574,
    "phone": "(561) 292-0232",
    "website": "https://copperhead-plumbing.com/",
    "address": "9250 Belvedere Rd STE 111, West Palm Beach, FL 33411, USA",
    "place_id": "ChIJzds_0pfZ2IgRSqL8qA5T5eo",
    "maps_url": "https://maps.google.com/?cid=16926026096971653706"
  },
  {
    "name": "Hi-Tech Plumbing, Air & Electrical",
    "rating": 4.7,
    "reviews": 774,
    "phone": "(561) 708-4989",
    "website": "http://www.hi-techplumbingandair.com/",
    "address": "1000 Stinson Way #111, West Palm Beach, FL 33411, USA",
    "place_id": "ChIJ1bYT09co2YgRQy9ez7M99ZY",
    "maps_url": "https://maps.google.com/?cid=10877668317470797635"
  },
  {
    "name": "Cleary Plumbing & Air",
    "rating": 4.9,
    "reviews": 1929,
    "phone": "(561) 954-3369",
    "website": "https://www.clearyplumbing.com/?utm_source=google&utm_medium=organic&utm_campaign=google-business-profile&utm_content=website",
    "address": "1011 8th Ave S, Lake Worth Beach, FL 33460, USA",
    "place_id": "ChIJwXzvc1kl2YgRsaR789VFKgU",
    "maps_url": "https://maps.google.com/?cid=372186704426804401"
  },
  {
    "name": "LCI Plumbing Services",
    "rating": 5,
    "reviews": 60,
    "phone": "(561) 201-8560",
    "website": "http://www.lciplumbingservices.com/",
    "address": "3584 Cabbage Palm Way, Loxahatchee, FL 33470, USA",
    "place_id": "ChIJKcGIUb7pLYcR6aXUwAt7EdQ",
    "maps_url": "https://maps.google.com/?cid=15281130301054821865"
  },
  {
    "name": "Garner Plumbing Inc",
    "rating": 5,
    "reviews": 12,
    "phone": "(561) 868-5595",
    "website": "",
    "address": "9581 Positano Way, Wellington, FL 33467, USA",
    "place_id": "ChIJobIJfxYn2YgRba_POo4DpCw",
    "maps_url": "https://maps.google.com/?cid=3216699943256305517"
  },
  {
    "name": "Service Max Pro",
    "rating": 5,
    "reviews": 94,
    "phone": "(954) 774-1850",
    "website": "http://servicemaxpro.net/",
    "address": "11981 Cypress Key Way, Royal Palm Beach, FL 33411, USA",
    "place_id": "ChIJN15U46Ev2YgRsonEB1Pxakk",
    "maps_url": "https://maps.google.com/?cid=5290306051214969266"
  },
  {
    "name": "Buckeye Plumbing Inc",
    "rating": 4.3,
    "reviews": 280,
    "phone": "(561) 282-5393",
    "website": "http://www.buckeyeplmg.com/",
    "address": "310 Business Park Way, West Palm Beach, FL 33411, USA",
    "place_id": "ChIJ686Wp94u2YgRJaVItKWQBxs",
    "maps_url": "https://maps.google.com/?cid=1947684405229692197"
  },
  {
    "name": "Wellington Handyman",
    "rating": 4.9,
    "reviews": 86,
    "phone": "(914) 447-8246",
    "website": "https://thewellingtonhandyman.com/",
    "address": "722 Lake Wellington Dr, Wellington, FL 33414, USA",
    "place_id": "ChIJC6Ggd8Ev2YgR_73v3TCiAj8",
    "maps_url": "https://maps.google.com/?cid=4540369705108487679"
  },
  {
    "name": "All Star Plumbing & Air",
    "rating": 4.7,
    "reviews": 1056,
    "phone": "(561) 667-2900",
    "website": "https://www.247allstar.com/",
    "address": "1544 Donna Rd, West Palm Beach, FL 33409, USA",
    "place_id": "ChIJc0YRsMcp2YgRhQwLQtbqzwo",
    "maps_url": "https://maps.google.com/?cid=779099466510306437"
  },
  {
    "name": "Roto-Rooter Plumbing & Water Cleanup",
    "rating": 4.9,
    "reviews": 1218,
    "phone": "(954) 903-9415",
    "website": "https://www.rotorooter.com/lakeworthfl/?utm_source=Google&utm_medium=organic&utm_campaign=gmb&utm_content=website",
    "address": "8461 Lake Worth Rd Suite 233E, Wellington, FL 33467, USA",
    "place_id": "ChIJ51x3iGgn2YgRhBCEdvw94fo",
    "maps_url": "https://maps.google.com/?cid=18077798533771300996"
  },
  {
    "name": "Accurate Plumbing Services Inc",
    "rating": 4.6,
    "reviews": 10,
    "phone": "(561) 968-0336",
    "website": "",
    "address": "8525 El Paso Dr A, Wellington, FL 33467, USA",
    "place_id": "ChIJ1ebuhwsm2YgRfF7yORdOs_Y",
    "maps_url": "https://maps.google.com/?cid=17776638015824879228"
  },
  {
    "name": "Shalom Plumbing & Septic",
    "rating": 4.8,
    "reviews": 17,
    "phone": "(561) 232-1887",
    "website": "http://www.shalomplumbing.com/",
    "address": "16700 E Secretariat Dr, Loxahatchee, FL 33470, USA",
    "place_id": "ChIJLZ3N8LIv2YgRSla52mYdq9k",
    "maps_url": "https://maps.google.com/?cid=15684662454841333322"
  },
  {
    "name": "Benjamin Franklin Plumbing of West Palm Beach",
    "rating": 4.8,
    "reviews": 435,
    "phone": "(561) 509-5325",
    "website": "https://www.benjaminfranklinplumbing.com/west-palm-beach/",
    "address": "8233 Gator Ln Ste 25b, West Palm Beach, FL 33411, USA",
    "place_id": "ChIJHbtKONAo2YgRFCefidHa-rg",
    "maps_url": "https://maps.google.com/?cid=13329206640648333076"
  },
  {
    "name": "Palm Beach Plumbing & Heater",
    "rating": 5,
    "reviews": 5,
    "phone": "(561) 225-2101",
    "website": "",
    "address": "9100 Belvedere Rd #146, Royal Palm Beach, FL 33411, USA",
    "place_id": "ChIJi9-pzKAv2YgRlHGxYMfVhIQ",
    "maps_url": "https://maps.google.com/?cid=9548992162229744020"
  },
  {
    "name": "Terrano Plumbing & Remodeling",
    "rating": 4.9,
    "reviews": 244,
    "phone": "(561) 477-3197",
    "website": "https://www.terranoplumbingandremodeling.com/",
    "address": "11444 Clear Creek Pl, Boca Raton, FL 33428, USA",
    "place_id": "ChIJ_XU6TMwb2YgRwnZOmnAgtEI",
    "maps_url": "https://maps.google.com/?cid=4806502370308421314"
  }
]