[
  {
    "name": "Othniel Electric llc",
    "rating": 4.8,
    "reviews": 23,
    "phone": "(386) 309-2388",
    "website": "",
    "address": "13759 120th St, Live Oak, FL 32060, USA",
    "place_id": "ChIJw16jECAgDQ0RDOtBld-9MYI",
    "maps_url": "https://maps.google.com/?cid=9381488266768935692"
  },
  {
    "name": "Ace Electrical Inc-North",
    "rating": 4,
    "reviews": 20,
    "phone": "(386) 362-4058",
    "website": "",
    "address": "8955 48th St, Live Oak, FL 32060, USA",
    "place_id": "ChIJH9Sswkbg7ogRo3CVkmGhF3g",
    "maps_url": "https://maps.google.com/?cid=8653562649458864291"
  },
  {
    "name": "Wood's Electrical Services Inc",
    "rating": 3.1,
    "reviews": 14,
    "phone": "(386) 364-5246",
    "website": "",
    "address": "5490 129th Rd, Live Oak, FL 32060, USA",
    "place_id": "ChIJq6rmaVzn7ogR1eAA6TLFRk8",
    "maps_url": "https://maps.google.com/?cid=5712469999814238421"
  },
  {
    "name": "Head Electric",
    "rating": 3.7,
    "reviews": 9,
    "phone": "(386) 362-6027",
    "website": "",
    "address": "PO Box 1132, Live Oak, FL 32064, USA",
    "place_id": "ChIJLclDaX3e7ogRBtm0CPWAqBg",
    "maps_url": "https://maps.google.com/?cid=1776811842899073286"
  },
  {
    "name": "Native Electric Service & Contracting, Inc.",
    "rating": 4,
    "reviews": 4,
    "phone": "(386) 688-5505",
    "website": "https://www.nativeelectricfl.com/",
    "address": "909 Suwannee Ave SW, Live Oak, FL 32064, USA",
    "place_id": "ChIJBwm2BZff7ogRrlqCTKR996E",
    "maps_url": "https://maps.google.com/?cid=11670935103965649582"
  },
  {
    "name": "Townsend Electrical Contractors, LLC",
    "rating": 5,
    "reviews": 81,
    "phone": "(386) 365-4643",
    "website": "https://townsendelectricalcontractorsl.godaddysites.com/?fbclid=PAAaaYL-WFXWLsQ-j1uPobHCGKtY2AaAE4x1GQBj5Gui_T47NkIHXzu-i8uUA",
    "address": "404 SW Barwick Ter, Lake City, FL 32024, USA",
    "place_id": "ChIJL3W41D0LwC4RFFYhekKDaIA",
    "maps_url": "https://maps.google.com/?cid=9252789755972769300"
  },
  {
    "name": "Affordable Electric",
    "rating": 4,
    "reviews": 3,
    "phone": "(386) 362-2035",
    "website": "",
    "address": "6437 57th Dr, Live Oak, FL 32060, USA",
    "place_id": "ChIJfWWAVH4f74gRKi_FlroqDAc",
    "maps_url": "https://maps.google.com/?cid=507827838867812138"
  },
  {
    "name": "City Electric Supply Live Oak",
    "rating": 4.3,
    "reviews": 14,
    "phone": "(386) 364-1973",
    "website": "https://www.cityelectricsupply.com/branches/fl/live-oak/live-oak",
    "address": "8874 101st Ct, Live Oak, FL 32060, USA",
    "place_id": "ChIJ1wvq2_Te7ogRC4Nkvq1aBTM",
    "maps_url": "https://maps.google.com/?cid=3676444373087978251"
  },
  {
    "name": "Brick Electric",
    "rating": 5,
    "reviews": 1,
    "phone": "",
    "website": "",
    "address": "9937 108th Trail, Live Oak, FL 32060, USA",
    "place_id": "ChIJb4mf2dXe7ogRB5PI7p1Ax5A",
    "maps_url": "https://maps.google.com/?cid=10432378108887208711"
  },
  {
    "name": "AAA Auto Electric",
    "rating": 4.6,
    "reviews": 27,
    "phone": "(386) 364-1206",
    "website": "https://usmapid.org/details/aaa-auto-electric-ChIJf2_",
    "address": "1302 Howard St E, Live Oak, FL 32064, USA",
    "place_id": "ChIJf2__zdbd7ogR8o-REFvkvRM",
    "maps_url": "https://maps.google.com/?cid=1422544137090076658"
  },
  {
    "name": "Everyday Electrical Services LLC",
    "rating": 5,
    "reviews": 20,
    "phone": "(352) 443-3775",
    "website": "https://www.everydayelectricalservices.com/?utm_source=google&utm_medium=wix_google_business_profile&utm_campaign=10061672796020068433",
    "address": "7839 SE 78th Pl, Trenton, FL 32693, USA",
    "place_id": "ChIJ77spbE3D6IgRuISpsrbLS0Q",
    "maps_url": "https://maps.google.com/?cid=4921251003374339256"
  },
  {
    "name": "Live Oak Electrical Services",
    "rating": 5,
    "reviews": 511,
    "phone": "(843) 505-1167",
    "website": "https://www.liveoakelectrical.com/",
    "address": "49 Browns Cove Rd #2A, Ridgeland, SC 29936, USA",
    "place_id": "ChIJ11qHzu2O-4gRmdiF9doHFgQ",
    "maps_url": "https://maps.google.com/?cid=294431462642800793"
  },
  {
    "name": "Fusion Electric Inc",
    "rating": 0,
    "reviews": 0,
    "phone": "(386) 364-3689",
    "website": "",
    "address": "11570 122nd St, Live Oak, FL 32060, USA",
    "place_id": "ChIJz1EB91vZ7ogRn_iHw_8-KBQ",
    "maps_url": "https://maps.google.com/?cid=1452480148045035679"
  },
  {
    "name": "B&D Electric, Inc.",
    "rating": 4.9,
    "reviews": 529,
    "phone": "(352) 472-1966",
    "website": "http://www.bdelectric.com/",
    "address": "24462 NW 9th Pl, Newberry, FL 32669, USA",
    "place_id": "ChIJUV2Az9jA6IgRvezOQSXBh3w",
    "maps_url": "https://maps.google.com/?cid=8973353148321033405"
  }
]