[
  {
    "name": "Tony's Electrical Services, LLC",
    "rating": 5,
    "reviews": 5,
    "phone": "(256) 324-8881",
    "website": "http://www.tonyselectricalservicesllc.com/",
    "address": "1410 Maryland Ave, Lynn Haven, FL 32444, USA",
    "place_id": "ChIJlyKuNAENqAcR26v8NVnD6Ro",
    "maps_url": "https://maps.google.com/?cid=1939295902484966363"
  },
  {
    "name": "C & Z Electrical Services LLC",
    "rating": 5,
    "reviews": 38,
    "phone": "(850) 899-2109",
    "website": "https://sites.google.com/czesllc.com/Czelectric/home",
    "address": "1010 Cornell Dr, Panama City, FL 32405, USA",
    "place_id": "ChIJr6ffp0-Dk4gRisRsVoWPxBQ",
    "maps_url": "https://maps.google.com/?cid=1496478779037238410"
  },
  {
    "name": "PC Beach Electric, LLC",
    "rating": 5,
    "reviews": 36,
    "phone": "(850) 596-3578",
    "website": "http://pcbeachelectric.com/",
    "address": "4224 Lorraine St, Panama City Beach, FL 32408, USA",
    "place_id": "ChIJpcnKe_WGk4gRjSd08IqyWbg",
    "maps_url": "https://maps.google.com/?cid=13283844885715363725"
  },
  {
    "name": "Kenny Strange Electric and Service Co, Inc",
    "rating": 4.5,
    "reviews": 47,
    "phone": "(850) 215-8030",
    "website": "https://www.facebook.com/KennyStrangeElectric/",
    "address": "2436 N East Ave, Panama City, FL 32405, USA",
    "place_id": "ChIJY3jZBz2Ck4gRV5_E11QioAM",
    "maps_url": "https://maps.google.com/?cid=261246526180073303"
  },
  {
    "name": "Whittaker Electric Inc",
    "rating": 4.7,
    "reviews": 41,
    "phone": "(850) 763-6296",
    "website": "https://whittakerelectric.com/",
    "address": "1108 School Ave, Panama City, FL 32401, USA",
    "place_id": "ChIJ5fqhe6uDk4gRhktWfIOl8s0",
    "maps_url": "https://maps.google.com/?cid=14840105706284534662"
  },
  {
    "name": "Hiller Plumbing, Heating, Cooling, & Electrical",
    "rating": 4.9,
    "reviews": 1291,
    "phone": "(850) 782-3513",
    "website": "https://happyhiller.com/locations/panama-city-beach/?utm_source=gmb&utm_medium=localseo&utm_campaign=local&se_campaign=Internet-LocalSEO",
    "address": "914 W 26th St, Lynn Haven, FL 32444, USA",
    "place_id": "ChIJ1f3HO1WBk4gRA0Jkg46k3TY",
    "maps_url": "https://maps.google.com/?cid=3953496979897860611"
  },
  {
    "name": "Peaden Air Conditioning, Plumbing & Electrical",
    "rating": 4.8,
    "reviews": 8519,
    "phone": "(850) 757-0074",
    "website": "https://www.peaden.com/panama-city?loc=panama-city&utm_source=gbp&utm_medium=organic&utm_campaign=panama-city-fl&utm_content=web-cta",
    "address": "618 W Baldwin Rd, Panama City, FL 32405, USA",
    "place_id": "ChIJk59NI5ODk4gR7VCZjhSPx9I",
    "maps_url": "https://maps.google.com/?cid=15188265586784817389"
  },
  {
    "name": "Complete Electric",
    "rating": 4.3,
    "reviews": 25,
    "phone": "(850) 258-4518",
    "website": "http://www.iheartelectric.com/",
    "address": "1203 Lindenwood Dr, Panama City, FL 32405, USA",
    "place_id": "ChIJyS7MTfmDk4gRQScE8W-4Nz8",
    "maps_url": "https://maps.google.com/?cid=4555312339033007937"
  },
  {
    "name": "Lucky’s Power",
    "rating": 5,
    "reviews": 5,
    "phone": "(850) 630-0405",
    "website": "http://luckyspower.com/",
    "address": "504 E 24th St, Lynn Haven, FL 32444, USA",
    "place_id": "ChIJgYew7LWHAKkRGllxOLeU0QI",
    "maps_url": "https://maps.google.com/?cid=203106972855261466"
  },
  {
    "name": "A&J Electrical",
    "rating": 4,
    "reviews": 1,
    "phone": "(850) 818-2914",
    "website": "https://a-electrical-1.ueniweb.com/?utm_campaign=gmb",
    "address": "4296 15St, Lynn Haven, FL 32444, USA",
    "place_id": "ChIJKyPg3GCDk4gRbiBPlYFNyHQ",
    "maps_url": "https://maps.google.com/?cid=8415061122692882542"
  },
  {
    "name": "MDC Electric Inc.",
    "rating": 4.7,
    "reviews": 20,
    "phone": "(850) 252-5173",
    "website": "http://mdcelectric.com/",
    "address": "1100 Oak Ave, Panama City, FL 32401, USA",
    "place_id": "ChIJXek4xQCGk4gRd33r3drXbbM",
    "maps_url": "https://maps.google.com/?cid=12929227440276602231"
  },
  {
    "name": "Bluewater Bay Generators, LLC",
    "rating": 4.2,
    "reviews": 15,
    "phone": "(850) 499-8296",
    "website": "http://bluewaterbaygenerator.com/",
    "address": "1306 Vermont Ave, Lynn Haven, FL 32444, USA",
    "place_id": "ChIJ95cx-Crzk4gRxZy9WYrbEcM",
    "maps_url": "https://maps.google.com/?cid=14056257299257597125"
  },
  {
    "name": "Jack Daniels Electric",
    "rating": 4.4,
    "reviews": 8,
    "phone": "(850) 769-9259",
    "website": "",
    "address": "1206 Maine Ave, Lynn Haven, FL 32444, USA",
    "place_id": "ChIJf6VHZcGDk4gRbHp3PnhwCC0",
    "maps_url": "https://maps.google.com/?cid=3244967193266846316"
  },
  {
    "name": "Telford Reynolds Electric",
    "rating": 4.3,
    "reviews": 66,
    "phone": "(850) 769-5800",
    "website": "http://www.telfordreynoldselectric.com/",
    "address": "2814 County Rd 390 suite c, Panama City, FL 32405, USA",
    "place_id": "ChIJA44B5YyCk4gREdkt88uJVaA",
    "maps_url": "https://maps.google.com/?cid=11553291928140110097"
  },
  {
    "name": "Shoreline Maintenance Group LLC",
    "rating": 4.9,
    "reviews": 103,
    "phone": "(850) 628-1177",
    "website": "",
    "address": "1511 Delaware Ave, Lynn Haven, FL 32444, USA",
    "place_id": "ChIJ3-jNzWFPW0YRIbtwLcHiTuU",
    "maps_url": "https://maps.google.com/?cid=16523393402187856673"
  },
  {
    "name": "Post Electric, Inc.",
    "rating": 5,
    "reviews": 8,
    "phone": "(850) 517-2344",
    "website": "https://www.postelectric.net/",
    "address": "3235 W Hwy 390, Panama City, FL 32405, USA",
    "place_id": "ChIJp_fUw42Dk4gRQ4UAEG5c1C0",
    "maps_url": "https://maps.google.com/?cid=3302366054554043715"
  },
  {
    "name": "Preston Link Electric",
    "rating": 4.9,
    "reviews": 326,
    "phone": "(352) 373-3516",
    "website": "https://prestonlinkelectric.com/",
    "address": "4000 SW 35th Terrace, Gainesville, FL 32608, USA",
    "place_id": "ChIJxasjZ9ii6IgRv_9Gmn6vUDc",
    "maps_url": "https://maps.google.com/?cid=3985878628511973311"
  },
  {
    "name": "Panhandle Signal Inc",
    "rating": 3,
    "reviews": 8,
    "phone": "(850) 271-3881",
    "website": "",
    "address": "2721 County Rd 390, Lynn Haven, FL 32444, USA",
    "place_id": "ChIJi5tULY2Ck4gRZVF6qbm2a0A",
    "maps_url": "https://maps.google.com/?cid=4642004749463998821"
  },
  {
    "name": "Blair Electric",
    "rating": 0,
    "reviews": 0,
    "phone": "(850) 873-6996",
    "website": "",
    "address": "3000 FL-77, Lynn Haven, FL 32444, USA",
    "place_id": "ChIJYxdIRrCDk4gREX8rNgTrom8",
    "maps_url": "https://maps.google.com/?cid=8044250287758343953"
  },
  {
    "name": "Manny's Electric",
    "rating": 4.9,
    "reviews": 77,
    "phone": "(352) 514-2035",
    "website": "",
    "address": "11032 NW 60 Terrace, Alachua, FL 32615, USA",
    "place_id": "ChIJN_jGbjW76IgRHx_sjJO9iew",
    "maps_url": "https://maps.google.com/?cid=17044362706182479647"
  },
  {
    "name": "Everyday Electrical Services LLC",
    "rating": 5,
    "reviews": 20,
    "phone": "(352) 443-3775",
    "website": "https://www.everydayelectricalservices.com/?utm_source=google&utm_medium=wix_google_business_profile&utm_campaign=10061672796020068433",
    "address": "7839 SE 78th Pl, Trenton, FL 32693, USA",
    "place_id": "ChIJ77spbE3D6IgRuISpsrbLS0Q",
    "maps_url": "https://maps.google.com/?cid=4921251003374339256"
  },
  {
    "name": "Tony's Electrical Services LLC",
    "rating": 1,
    "reviews": 2,
    "phone": "(256) 324-8881",
    "website": "http://tonyselectricalservicesllc.com/",
    "address": "330 W 23rd St F, Panama City, FL 32405, USA",
    "place_id": "ChIJCanm7oaDk4gRL6M81ZGhz3s",
    "maps_url": "https://maps.google.com/?cid=8921527034564092719"
  },
  {
    "name": "Winsupply of Bay County Electrical",
    "rating": 4.9,
    "reviews": 8,
    "phone": "(850) 271-5405",
    "website": "http://www.unitedlighting.com/",
    "address": "201 Business Park Dr, Lynn Haven, FL 32444, USA",
    "place_id": "ChIJ9zZY0ACDk4gRA3FgMkK_uYo",
    "maps_url": "https://maps.google.com/?cid=9996231138959454467"
  },
  {
    "name": "Keefe & Son's Electric, Inc",
    "rating": 5,
    "reviews": 2,
    "phone": "(850) 819-5729",
    "website": "http://www.keefeandsonselectric.com/",
    "address": "2431 US-231 A, Panama City, FL 32405, USA",
    "place_id": "ChIJz8-njGCDk4gRNa_4uaYphvs",
    "maps_url": "https://maps.google.com/?cid=18124219546460532533"
  },
  {
    "name": "TCS Electrical Co",
    "rating": 3.7,
    "reviews": 3,
    "phone": "(844) 827-1040",
    "website": "http://www.tcselectrical.com/",
    "address": "2009 Poplar Pl, Panama City, FL 32405, USA",
    "place_id": "ChIJI-bs4gE_kYgRZIEja0ON8w4",
    "maps_url": "https://maps.google.com/?cid=1077360056571494756"
  }
]