[
  {
    "name": "Joel Foy Electrical Service",
    "rating": 4.8,
    "reviews": 650,
    "phone": "(850) 562-3691",
    "website": "https://joelfoyelectric.com/",
    "address": "5650 Gum Rd, Tallahassee, FL 32304, USA",
    "place_id": "ChIJc_VK3Wnx7IgR28a_0pTZqJw",
    "maps_url": "https://maps.google.com/?cid=11288511699218319067"
  },
  {
    "name": "A+ Electrical Contractors LLC",
    "rating": 4.7,
    "reviews": 33,
    "phone": "(850) 509-9926",
    "website": "http://www.aplusec.com/",
    "address": "956 Yulee St, Tallahassee, FL 32304, USA",
    "place_id": "ChIJuVh0j5b07IgRcWj7aEIvjsc",
    "maps_url": "https://maps.google.com/?cid=14379482622516226161"
  },
  {
    "name": "GT Electric",
    "rating": 4.6,
    "reviews": 158,
    "phone": "(850) 655-0868",
    "website": "https://gtelectricfl.com/?utm_campaign=gmb",
    "address": "3154 Eliza Rd, Tallahassee, FL 32308, USA",
    "place_id": "ChIJj4BLMDNf7IgRBlbIxOoBOqY",
    "maps_url": "https://maps.google.com/?cid=11977888266780694022"
  },
  {
    "name": "Weston Trawick, Inc.",
    "rating": 4.7,
    "reviews": 77,
    "phone": "(850) 514-0003",
    "website": "http://www.westontrawick.com/",
    "address": "5392 Tower Rd, Tallahassee, FL 32303, USA",
    "place_id": "ChIJAckzlzvx7IgRwfbsUYippns",
    "maps_url": "https://maps.google.com/?cid=8909995315754235585"
  },
  {
    "name": "Lawson & Lawson Electrical Services",
    "rating": 4.7,
    "reviews": 143,
    "phone": "(850) 562-4111",
    "website": "http://www.llelectrical.com/",
    "address": "5019 Metzke Ln, Tallahassee, FL 32303, USA",
    "place_id": "ChIJ5-0V2kDx7IgRN_rwNUq173Q",
    "maps_url": "https://maps.google.com/?cid=8426152758170679863"
  },
  {
    "name": "Meeks Electrical Services",
    "rating": 4,
    "reviews": 50,
    "phone": "(850) 575-5241",
    "website": "https://meekselectrical.com/",
    "address": "4971 Capital Cir SE, Tallahassee, FL 32311, USA",
    "place_id": "ChIJf-jGsRha7IgR4bqf9SNZdXA",
    "maps_url": "https://maps.google.com/?cid=8103481115502688993"
  },
  {
    "name": "Sun Coast Electric & Networking",
    "rating": 4.6,
    "reviews": 27,
    "phone": "(850) 514-3989",
    "website": "https://www.suncoastelectric.com/",
    "address": "3476 Garber Dr, Tallahassee, FL 32303, USA",
    "place_id": "ChIJr8h3wojz7IgR2r8iFIoH_2Y",
    "maps_url": "https://maps.google.com/?cid=7421659000554569690"
  },
  {
    "name": "Florida Electric Inc",
    "rating": 5,
    "reviews": 4,
    "phone": "(850) 574-3355",
    "website": "http://www.floridaelectricinc.com/",
    "address": "4525 Capital Cir NW # J19, Tallahassee, FL 32303, USA",
    "place_id": "ChIJq_2-70Xx7IgR-2DGEhiD2X4",
    "maps_url": "https://maps.google.com/?cid=9140481058142576891"
  },
  {
    "name": "Truevolt Electrical Services Inc",
    "rating": 4.9,
    "reviews": 154,
    "phone": "(850) 443-0896",
    "website": "http://www.truevoltelectric.com/",
    "address": "4786 Woodlane Cir Apartment A, Tallahassee, FL 32303, USA",
    "place_id": "ChIJV0SV3Z1Z7IgR0MGV-fxqIqA",
    "maps_url": "https://maps.google.com/?cid=11538902830028276176"
  },
  {
    "name": "Light Force Electrical Services",
    "rating": 3,
    "reviews": 12,
    "phone": "(850) 661-0194",
    "website": "https://www.lightforceelectricalservices.com/",
    "address": "2490 Centerville Rd, Tallahassee, FL 32308, USA",
    "place_id": "ChIJ3XnK3-NZ7IgRE3AAaT03ulI",
    "maps_url": "https://maps.google.com/?cid=5961137793672441875"
  },
  {
    "name": "Rocafort Electrical Services, LLC",
    "rating": 4.6,
    "reviews": 10,
    "phone": "(850) 509-3650",
    "website": "https://rocafortelectric.com/",
    "address": "2113 Great Oak Dr, Tallahassee, FL 32303, USA",
    "place_id": "ChIJZTSnmZT17IgRupiJAWt5QsQ",
    "maps_url": "https://maps.google.com/?cid=14141999280391035066"
  },
  {
    "name": "All Florida Electric Inc.",
    "rating": 5,
    "reviews": 2,
    "phone": "(850) 576-0593",
    "website": "",
    "address": "1219 Blountstown St, Tallahassee, FL 32304, USA",
    "place_id": "ChIJOf2Roof07IgRnnaa1oiAVkg",
    "maps_url": "https://maps.google.com/?cid=5212494943932282526"
  },
  {
    "name": "Electrician Pros Tallahassee",
    "rating": 0,
    "reviews": 0,
    "phone": "(850) 378-4104",
    "website": "",
    "address": "401 W Park Ave #207, Tallahassee, FL 32301, USA",
    "place_id": "ChIJ1apft-717IgRlANQb5cPjsU",
    "maps_url": "https://maps.google.com/?cid=14235332615246709652"
  },
  {
    "name": "Mathers Electric Co., Inc",
    "rating": 4.4,
    "reviews": 77,
    "phone": "(850) 576-2342",
    "website": "https://matherselectric.com/",
    "address": "4834 Corlett St, Tallahassee, FL 32303, USA",
    "place_id": "ChIJNxJgekfx7IgRuoh5K3KapxA",
    "maps_url": "https://maps.google.com/?cid=1200097640863860922"
  },
  {
    "name": "Big Bend Electric Inc",
    "rating": 4.5,
    "reviews": 2,
    "phone": "(850) 576-6694",
    "website": "",
    "address": "5539 Emma Ash Pl, Tallahassee, FL 32311, USA",
    "place_id": "ChIJK5F4KwFo7IgRp3slkWC4ujM",
    "maps_url": "https://maps.google.com/?cid=3727494366494030759"
  },
  {
    "name": "Rocafort Electrical Services, LLC",
    "rating": 4.9,
    "reviews": 51,
    "phone": "(850) 509-3650",
    "website": "https://rocafortelectric.com/",
    "address": "4825 Woodlane Cir Apartment 103, Tallahassee, FL 32303, USA",
    "place_id": "ChIJBbZ27kvx7IgRClvzrN61hnU",
    "maps_url": "https://maps.google.com/?cid=8468656117305793290"
  },
  {
    "name": "Fraser Electric Inc.",
    "rating": 4.3,
    "reviews": 41,
    "phone": "(850) 575-3628",
    "website": "https://fraserelectric.com/",
    "address": "5084 Louvinia Dr, Tallahassee, FL 32311, USA",
    "place_id": "ChIJncQlt5Fa7IgRUR7LdzBpizY",
    "maps_url": "https://maps.google.com/?cid=3930350756700036689"
  },
  {
    "name": "Lewis & Thompson Electrical",
    "rating": 4.3,
    "reviews": 6,
    "phone": "(850) 576-6249",
    "website": "",
    "address": "2906 Plant St, Tallahassee, FL 32304, USA",
    "place_id": "ChIJ8QExJpT07IgRtoCCegP4IO0",
    "maps_url": "https://maps.google.com/?cid=17086929680067625142"
  },
  {
    "name": "Chad O'Hara's Quality Electrical Services Inc.",
    "rating": 4,
    "reviews": 35,
    "phone": "(850) 666-3375",
    "website": "",
    "address": "1130 Thomasville Rd, Tallahassee, FL 32303, USA",
    "place_id": "ChIJG6C5qJD17IgRdvhCYsyUez4",
    "maps_url": "https://maps.google.com/?cid=4502355858029738102"
  },
  {
    "name": "Walsh Consulting and Electrical",
    "rating": 4.6,
    "reviews": 13,
    "phone": "(850) 562-9327",
    "website": "http://www.electriciantallahassee.net/",
    "address": "5301 Capital Cir SW, Tallahassee, FL 32305, USA",
    "place_id": "ChIJ17cxSbv17IgRVYM3VFYDa5g",
    "maps_url": "https://maps.google.com/?cid=10982875785588081493"
  },
  {
    "name": "Albritton Electrical Service, Inc",
    "rating": 4.8,
    "reviews": 19,
    "phone": "(850) 562-1193",
    "website": "https://albrittonelectric.com/",
    "address": "4821 6 Oaks Dr, Tallahassee, FL 32303, USA",
    "place_id": "ChIJ_3cqYQDx7IgRrIQbwgwvx40",
    "maps_url": "https://maps.google.com/?cid=10216186011555955884"
  },
  {
    "name": "Macon Electric LLC",
    "rating": 5,
    "reviews": 21,
    "phone": "(850) 510-0943",
    "website": "https://usmapiz.org/details/macon-electric-llc-ChIJy8f",
    "address": "10720 Sycamore Ridge Ln, Tallahassee, FL 32305, USA",
    "place_id": "ChIJy8ftV0th7IgRHU1GWIXrM1Q",
    "maps_url": "https://maps.google.com/?cid=6067452080942370077"
  },
  {
    "name": "Peaden Air Conditioning, Plumbing & Electrical",
    "rating": 4.9,
    "reviews": 452,
    "phone": "(850) 629-0028",
    "website": "https://www.peaden.com/tallahassee?loc=tallahassee&utm_source=gbp&utm_medium=organic&utm_campaign=tallahassee-fl&utm_content=web-cta",
    "address": "3970 S Century Park Cir, Tallahassee, FL 32304, USA",
    "place_id": "ChIJOR2SA7_17IgRr-X1hz7zqqw",
    "maps_url": "https://maps.google.com/?cid=12442024370458977711"
  },
  {
    "name": "Metro Electrical Services, Inc.",
    "rating": 4.2,
    "reviews": 16,
    "phone": "(850) 222-2804",
    "website": "http://www.metroelectricalservices.com/",
    "address": "4404 Blountstown Hwy, Tallahassee, FL 32304, USA",
    "place_id": "ChIJU5t0GGLz7IgRJBqZJEk_bQk",
    "maps_url": "https://maps.google.com/?cid=679268702181988900"
  },
  {
    "name": "Northeast Electrical, llc",
    "rating": 5,
    "reviews": 9,
    "phone": "(850) 728-5943",
    "website": "https://neelectricservice.com/",
    "address": "7061 John Wayne Ct, Tallahassee, FL 32305, USA",
    "place_id": "ChIJBzHXhFqN7IgRIToEfG5mc1Q",
    "maps_url": "https://maps.google.com/?cid=6085320146220759585"
  }
]