[
  {
    "name": "Best Roofing",
    "rating": 4.7,
    "reviews": 332,
    "phone": "(888) 884-6091",
    "website": "https://www.bestroofing.net/",
    "address": "1600 NE 12th Terrace, Fort Lauderdale, FL 33305, USA",
    "place_id": "ChIJg3ZtK70B2YgR1LUN8l1GhNg",
    "maps_url": "https://maps.google.com/?cid=15601672378425128404"
  },
  {
    "name": "Kairos Roofing",
    "rating": 4.8,
    "reviews": 479,
    "phone": "(954) 787-4026",
    "website": "https://www.kairosroofingllc.com/?UTM_source=GMB_listing&UTM_medium=organic",
    "address": "2190 W State Rd 84, Fort Lauderdale, FL 33312, USA",
    "place_id": "ChIJrWVUBp0H2YgRrHIF_mEDET0",
    "maps_url": "https://maps.google.com/?cid=4400302030326166188"
  },
  {
    "name": "Maze Roofing Fort Lauderdale",
    "rating": 5,
    "reviews": 151,
    "phone": "(754) 258-4590",
    "website": "https://mazeroofingfortlauderdale.com/",
    "address": "5731 NE 14th Ave Unit B, Fort Lauderdale, FL 33334, USA",
    "place_id": "ChIJHe5kDXsD2YgRyrJQmVG7jN4",
    "maps_url": "https://maps.google.com/?cid=16036398332298441418"
  },
  {
    "name": "Paul Bange Roofing, Inc.",
    "rating": 4.9,
    "reviews": 2501,
    "phone": "(954) 981-7663",
    "website": "https://www.paulbangeroofing.com/",
    "address": "7000 SW 21st Pl, Davie, FL 33317, USA",
    "place_id": "ChIJ5Q8y6IYH2YgRE31sq_hDxlQ",
    "maps_url": "https://maps.google.com/?cid=6108644679881620755"
  },
  {
    "name": "Advanced Roofing Inc",
    "rating": 4.5,
    "reviews": 120,
    "phone": "(954) 522-6868",
    "website": "https://www.advancedroofing.com/",
    "address": "1950 NW 22nd St, Fort Lauderdale, FL 33311, USA",
    "place_id": "ChIJYzmZpkAB2YgRoZ-YPCC3IIU",
    "maps_url": "https://maps.google.com/?cid=9592868555382628257"
  },
  {
    "name": "Tiger Team Roofing",
    "rating": 4.8,
    "reviews": 299,
    "phone": "(954) 833-8591",
    "website": "https://www.tigerteamroofing.com/?utm_source=GMB&utm_medium=local",
    "address": "5311 NW 22nd Ave, Fort Lauderdale, FL 33309, USA",
    "place_id": "ChIJo4Ti9u4D2YgRApyDDPrzdaI",
    "maps_url": "https://maps.google.com/?cid=11706531061696797698"
  },
  {
    "name": "Nast Roofing Co",
    "rating": 4.6,
    "reviews": 351,
    "phone": "(954) 475-0610",
    "website": "http://www.nastroofing.com/?utm_source=gbp&utm_medium=organic&utm_campaign=gbp-listing",
    "address": "138 W State Rd 84, Fort Lauderdale, FL 33315, USA",
    "place_id": "ChIJy0x41HwA2YgRkpiCqKQ1BX8",
    "maps_url": "https://maps.google.com/?cid=9152780799018440850"
  },
  {
    "name": "Ultra Roof Repair Fort Lauderdale",
    "rating": 5,
    "reviews": 19,
    "phone": "(954) 594-8655",
    "website": "https://ultraroofrepair.com/fort-lauderdale/",
    "address": "110 SE 6th St #3292, Fort Lauderdale, FL 33301, USA",
    "place_id": "ChIJJ890xeoB2YgRBVWIcsPCShY",
    "maps_url": "https://maps.google.com/?cid=1606310361806951685"
  },
  {
    "name": "same day roof repair Fort Lauderdale",
    "rating": 4.8,
    "reviews": 17,
    "phone": "(954) 710-8253",
    "website": "https://samedayroofrepairllc.com/",
    "address": "955 Federal Hwy #591, Fort Lauderdale, FL 33316, USA",
    "place_id": "ChIJFXA_fYQB2YgRNj6Mr4Hvzz8",
    "maps_url": "https://maps.google.com/?cid=4598157084843589174"
  },
  {
    "name": "JDM Roofing Repair & Installation",
    "rating": 5,
    "reviews": 43,
    "phone": "(954) 727-5425",
    "website": "https://jdmroofingexperts.com/",
    "address": "721 NE 3rd Ave d, Fort Lauderdale, FL 33304, USA",
    "place_id": "ChIJSbYtwQoB2YgRFQYolhtAcvE",
    "maps_url": "https://maps.google.com/?cid=17398038797713147413"
  },
  {
    "name": "Ricketts Roofing And Construction",
    "rating": 4.7,
    "reviews": 96,
    "phone": "(954) 588-5670",
    "website": "http://www.rickettsconstruction.com/",
    "address": "4987 N University Dr #17, Lauderhill, FL 33351, USA",
    "place_id": "ChIJE6hXJN0F2YgREVemKWAhVCk",
    "maps_url": "https://maps.google.com/?cid=2978041950498084625"
  },
  {
    "name": "Allied Roofing & Sheet Metal, Inc.",
    "rating": 4.8,
    "reviews": 244,
    "phone": "(954) 485-5922",
    "website": "http://www.alliedroofingfl.com/",
    "address": "2801 NW 55th Ct bldg 1, Tamarac, FL 33309, USA",
    "place_id": "ChIJnfrUSA0C2YgR1vGWg4s2zUI",
    "maps_url": "https://maps.google.com/?cid=4813563549564989910"
  },
  {
    "name": "Ricketts Roofing And Construction",
    "rating": 4.8,
    "reviews": 107,
    "phone": "(954) 588-5670",
    "website": "https://rickettsroofing.com/",
    "address": "1211 NW 29th Way, Fort Lauderdale, FL 33311, USA",
    "place_id": "ChIJ9W5JrLUB2YgRdjZTSxhCZKQ",
    "maps_url": "https://maps.google.com/?cid=11845665592001640054"
  },
  {
    "name": "Gold Coast Construction LLC - Roofing Contractor",
    "rating": 5,
    "reviews": 10,
    "phone": "(786) 475-7742",
    "website": "https://gccrfg.com/",
    "address": "2713 NW 55th Way, Fort Lauderdale, FL 33313, USA",
    "place_id": "ChIJZ0_m7DkH2YgRdJXFgYlUuAY",
    "maps_url": "https://maps.google.com/?cid=484229909506790772"
  },
  {
    "name": "Advanced Roofing & Construction LLC",
    "rating": 4.9,
    "reviews": 103,
    "phone": "(954) 540-3135",
    "website": "http://www.advancedroofingnconstruction.com/",
    "address": "2071 SW 10th St Unit G4, Davie, FL 33317, USA",
    "place_id": "ChIJATMX-04H2YgRYyKyGLPPXwo",
    "maps_url": "https://maps.google.com/?cid=747544431287214691"
  },
  {
    "name": "All American Roofing",
    "rating": 4.6,
    "reviews": 129,
    "phone": "(954) 772-7663",
    "website": "https://www.allamericanroof.com/",
    "address": "944 Prospect Rd, Oakland Park, FL 33309, USA",
    "place_id": "ChIJk-EtkNkD2YgRNCxbCRMCLUo",
    "maps_url": "https://maps.google.com/?cid=5344930613543250996"
  },
  {
    "name": "Trust Guard Roofing Company",
    "rating": 4.9,
    "reviews": 74,
    "phone": "(786) 952-6682",
    "website": "https://tgroofingcompany.com/",
    "address": "2905 Stirling Rd, Fort Lauderdale, FL 33312, USA",
    "place_id": "ChIJ7ZSJAuqr2YgRytuDjtOtjzM",
    "maps_url": "https://maps.google.com/?cid=3715379341744659402"
  },
  {
    "name": "Florida Quality Roofing, Inc.",
    "rating": 4.9,
    "reviews": 150,
    "phone": "(305) 306-7663",
    "website": "http://www.floridaqualityroofing.com/",
    "address": "2421 NE 4th Ave, Pompano Beach, FL 33064, USA",
    "place_id": "ChIJj8vxJ4Gr2YgRCmmFrIXeqy0",
    "maps_url": "https://maps.google.com/?cid=3290968618430720266"
  },
  {
    "name": "Power Roofing & Siding Fort Lauderdale",
    "rating": 5,
    "reviews": 12,
    "phone": "(954) 350-0022",
    "website": "http://powerroofingmiami.com/",
    "address": "2754 N Federal Hwy, Fort Lauderdale, FL 33306, USA",
    "place_id": "ChIJKUiYT4oB2YgRmSKojpYHBpA",
    "maps_url": "https://maps.google.com/?cid=10377990734541759129"
  },
  {
    "name": "RHI Roofing",
    "rating": 4.8,
    "reviews": 180,
    "phone": "(954) 290-3992",
    "website": "http://www.rhiroofing.com/",
    "address": "721 NE 42nd St, Oakland Park, FL 33334, USA",
    "place_id": "ChIJQ8zQEekD2YgRLSj0_OqVFac",
    "maps_url": "https://maps.google.com/?cid=12039694015343634477"
  },
  {
    "name": "Dolphin Roofing - Roof Repair & Replacement",
    "rating": 5,
    "reviews": 70,
    "phone": "(954) 655-2424",
    "website": "http://dolphinroofing.com/",
    "address": "1524 NE 36th St, Oakland Park, FL 33334, USA",
    "place_id": "ChIJ98ndrDgC2YgRUdRTOZo0iKI",
    "maps_url": "https://maps.google.com/?cid=11711668667968377937"
  },
  {
    "name": "MIW Roofing",
    "rating": 5,
    "reviews": 399,
    "phone": "(954) 918-1199",
    "website": "https://miwroofing.com/",
    "address": "404 NE 38th St, Oakland Park, FL 33334, USA",
    "place_id": "ChIJcaf-bxoB2YgRWmb70h7NtfM",
    "maps_url": "https://maps.google.com/?cid=17561167854273521242"
  },
  {
    "name": "LaPorta Roofing",
    "rating": 5,
    "reviews": 46,
    "phone": "(561) 287-9331",
    "website": "https://laportaroofing.com/",
    "address": "2821 E Commercial Blvd Suite 219, Fort Lauderdale, FL 33308, USA",
    "place_id": "ChIJCziRinUD2YgRckHxa0iV1U8",
    "maps_url": "https://maps.google.com/?cid=5752668237316833650"
  },
  {
    "name": "Commercial Roofing Industries",
    "rating": 4.9,
    "reviews": 30,
    "phone": "(954) 317-2500",
    "website": "https://commercialroofingindustries.com/",
    "address": "1864 NW 38th Ave #4, Fort Lauderdale, FL 33311, USA",
    "place_id": "ChIJf5oxaykH2YgRb11U4vztKGY",
    "maps_url": "https://maps.google.com/?cid=7361395261321796975"
  },
  {
    "name": "Roofing Fort Lauderdale",
    "rating": 5,
    "reviews": 6,
    "phone": "(954) 589-1577",
    "website": "https://roofersfortlauderdale.com/",
    "address": "5911 SW 39th Ave, Fort Lauderdale, FL 33312, USA",
    "place_id": "ChIJW1Gt9vCp2YgRiZt-LNvY5fU",
    "maps_url": "https://maps.google.com/?cid=17718806744815016841"
  }
]