[
  {
    "name": "Native Pest Management",
    "rating": 5,
    "reviews": 1083,
    "phone": "(850) 637-8341",
    "website": "https://www.nativepestmanagement.com/contact-us/?utm_source=google&utm_medium=organic&utm_campaign=local-seo",
    "address": "2420 Lakeshore Dr, Tallahassee, FL 32312, USA",
    "place_id": "ChIJbZfx2deQaiIRx-OqtJZqBrE",
    "maps_url": "https://maps.google.com/?cid=12756000190082245575"
  },
  {
    "name": "Capelouto Termite & Pest Control",
    "rating": 4.9,
    "reviews": 831,
    "phone": "(850) 273-5647",
    "website": "https://www.capeloutopestcontrol.com/?utm_source=google&utm_medium=gbp&utm_campaign=tallahassee",
    "address": "4970 Capital Cir NW, Tallahassee, FL 32303, USA",
    "place_id": "ChIJkwhUrKpf7IgRymaNg_wennw",
    "maps_url": "https://maps.google.com/?cid=8979648776911021770"
  },
  {
    "name": "Truly Nolen Pest & Termite Control - Tallahassee",
    "rating": 5,
    "reviews": 456,
    "phone": "(850) 765-4496",
    "website": "https://www.trulynolen.com/franchise/tallahassee-fl",
    "address": "1172 Capital Cir SE, Tallahassee, FL 32301, USA",
    "place_id": "ChIJmeeC4WNb7IgRSLHGvufAXHc",
    "maps_url": "https://maps.google.com/?cid=8600961489941475656"
  },
  {
    "name": "Florida Pest Control",
    "rating": 4.7,
    "reviews": 519,
    "phone": "(850) 518-6859",
    "website": "https://www.flapest.com/locations/tallahassee/?utm_source=google&utm_medium=gbp&utm_campaign=tallahassee",
    "address": "4970 Capital Cir NW, Tallahassee, FL 32303, USA",
    "place_id": "ChIJMXjnCDjx7IgRrg8hOWy_o14",
    "maps_url": "https://maps.google.com/?cid=6819504732304904110"
  },
  {
    "name": "Paul's Termite & Pest Control",
    "rating": 4.8,
    "reviews": 1015,
    "phone": "(850) 222-6808",
    "website": "https://www.callpauls.com/?utm_source=GMB&utm_medium=organic&utm_campaign=GMB-Tallahassee",
    "address": "1725 Mahan Dr, Tallahassee, FL 32308, USA",
    "place_id": "ChIJM9ksiR_y7IgRR4lr4u3maPE",
    "maps_url": "https://maps.google.com/?cid=17395407470098876743"
  },
  {
    "name": "McCall Pest & Wildlife - Tallahassee",
    "rating": 4.9,
    "reviews": 343,
    "phone": "(850) 498-4480",
    "website": "https://www.mccallservice.com/our-service-areas/tallahassee-pest-control/",
    "address": "5149 Woodlane Cir, Tallahassee, FL 32303, USA",
    "place_id": "ChIJIVi591L17IgRwbDgt5Z8KwY",
    "maps_url": "https://maps.google.com/?cid=444585974998020289"
  },
  {
    "name": "Capital City Pest Control",
    "rating": 5,
    "reviews": 23,
    "phone": "(850) 694-7056",
    "website": "",
    "address": "3701 Houston Rd, Tallahassee, FL 32304, USA",
    "place_id": "ChIJs6paiy3x7IgReKjgKttyHlY",
    "maps_url": "https://maps.google.com/?cid=6205523622205892728"
  },
  {
    "name": "Arrow Exterminators",
    "rating": 4.8,
    "reviews": 129,
    "phone": "(850) 688-9043",
    "website": "http://www.arrowexterminators.com/florida/tallahassee-service-center",
    "address": "3642 Peddie Dr, Tallahassee, FL 32303, USA",
    "place_id": "ChIJqfbTWrD17IgRg_Obp8EVcc4",
    "maps_url": "https://maps.google.com/?cid=14875694965666345859"
  },
  {
    "name": "Integrated Pest Management",
    "rating": 4.9,
    "reviews": 49,
    "phone": "(850) 272-0212",
    "website": "https://business.google.com/site/l/07701692887637160304",
    "address": "Florida 32303, USA",
    "place_id": "ChIJddVbn6Dx7IgR-_2f7X9CTJc",
    "maps_url": "https://maps.google.com/?cid=10902161915172093435"
  },
  {
    "name": "ProForce Pest Control - Tallahassee",
    "rating": 4.6,
    "reviews": 684,
    "phone": "(448) 206-0181",
    "website": "https://proforcepest.com/where-we-service/tallahassee-fl-pest-control/?utm_source=gmb&utm_medium=organic&utm_campaign=gbp&utm_content=tallahassee_fl",
    "address": "502 Capital Cir SE STE. D3, Tallahassee, FL 32301, USA",
    "place_id": "ChIJqY1EETFf7IgRKTcjE3AZ0F4",
    "maps_url": "https://maps.google.com/?cid=6831988603869148969"
  },
  {
    "name": "Rock Solid Termite & Pest Control",
    "rating": 4.9,
    "reviews": 43,
    "phone": "(850) 386-7872",
    "website": "http://www.rocksolidpest.com/",
    "address": "1535 Killearn Center Blvd Suite B-3, Tallahassee, FL 32309, USA",
    "place_id": "ChIJ_acXxsdY7IgRXMJprmwoOf0",
    "maps_url": "https://maps.google.com/?cid=18246659812516020828"
  },
  {
    "name": "Orkin",
    "rating": 4.8,
    "reviews": 411,
    "phone": "(850) 391-5608",
    "website": "https://www.orkin.com/locations/florida-fl/tallahassee-pest-control/branch-236?utm_source=local&utm_medium=local&utm_campaign=LCL0356X",
    "address": "850 Blountstown St, Tallahassee, FL 32304, USA",
    "place_id": "ChIJ-R-hOjfx7IgRN-C5_b9OjpU",
    "maps_url": "https://maps.google.com/?cid=10776637544846712887"
  },
  {
    "name": "Dads Pest Control",
    "rating": 5,
    "reviews": 46,
    "phone": "(850) 590-3200",
    "website": "https://www.dadspest.com/?utm_source=google&utm_medium=wix_google_business_profile&utm_campaign=18260424617871870843",
    "address": "8726 Palencia Ct, Tallahassee, FL 32311, USA",
    "place_id": "ChIJ-zqEsu31s2ARX1JI2_hX_dQ",
    "maps_url": "https://maps.google.com/?cid=15347519831490974303"
  },
  {
    "name": "PGS Lawn & Pest",
    "rating": 5,
    "reviews": 15,
    "phone": "(850) 688-9625",
    "website": "https://pgslawnandpest.com/",
    "address": "4525 Capital Cir NW STE I-31, Tallahassee, FL 32303, USA",
    "place_id": "ChIJ4Vr1xbDx7IgR7NXkxOlQ-rk",
    "maps_url": "https://maps.google.com/?cid=13401112606155265516"
  },
  {
    "name": "Barber's Best Termite and Pest",
    "rating": 4.9,
    "reviews": 54,
    "phone": "(850) 562-5765",
    "website": "http://barbersbestpest.com/",
    "address": "2605 Oak Ln Dr, Tallahassee, FL 32308, USA",
    "place_id": "ChIJAQCEjydY7IgR2Ry_0oOJUP0",
    "maps_url": "https://maps.google.com/?cid=18253240489002081497"
  },
  {
    "name": "Selrahc Termite & Pest Control",
    "rating": 5,
    "reviews": 50,
    "phone": "(850) 745-5335",
    "website": "https://selrahcpest.com/",
    "address": "447 Merlin Way, Tallahassee, FL 32301, USA",
    "place_id": "ChIJb6SmxkBf7IgR3u_w1etVw_8",
    "maps_url": "https://maps.google.com/?cid=18429668571525214174"
  },
  {
    "name": "1st Choice Pest Services",
    "rating": 4.4,
    "reviews": 28,
    "phone": "(850) 656-5982",
    "website": "http://www.1stchoicepest.com/",
    "address": "271 Hidden Pond Ct, Tallahassee, FL 32317, USA",
    "place_id": "ChIJ27s_rZ9e7IgRCa5ki-82_tE",
    "maps_url": "https://maps.google.com/?cid=15131592200475160073"
  },
  {
    "name": "Florida Bug Control",
    "rating": 4.9,
    "reviews": 222,
    "phone": "(855) 624-2847",
    "website": "http://www.floridabugcontrol.com/",
    "address": "177 SW Range Ave Ste A, Madison, FL 32340, USA",
    "place_id": "ChIJCcmhdqeCkykRydQmmA3slgg",
    "maps_url": "https://maps.google.com/?cid=618941541941433545"
  },
  {
    "name": "Terminix",
    "rating": 4.7,
    "reviews": 512,
    "phone": "(850) 328-5500",
    "website": "https://www.terminix.com/exterminators/fl/tallahassee-2207/?utm_source=gmb-listing&utm_medium=organic&utm_campaign=local&utm_term=tallahassee",
    "address": "4970 Capital Cir NW, Tallahassee, FL 32303, USA",
    "place_id": "ChIJraibP_5e7IgRprWhHHdD6VY",
    "maps_url": "https://maps.google.com/?cid=6262610935695914406"
  },
  {
    "name": "Termite & Pest Control & Dryer Vent Cleaning Services Tallahassee, FL",
    "rating": 4.9,
    "reviews": 10,
    "phone": "(321) 341-4449",
    "website": "",
    "address": "1880 Page Rd, Tallahassee, FL 32305, USA",
    "place_id": "ChIJoQHMrI1h7IgRWooxPIZPvRk",
    "maps_url": "https://maps.google.com/?cid=1854726059500603994"
  },
  {
    "name": "Massey Services Pest Control",
    "rating": 4.5,
    "reviews": 110,
    "phone": "(850) 656-7222",
    "website": "https://www.masseyservices.com/service-location/south-tallahassee-pest-control/?utm_source=googlemybusiness&utm_medium=search&utm_content=Tallahassee57&utm_campaign=masseylocalsearch",
    "address": "3217 Apalachee Pkwy Ste B, Tallahassee, FL 32311, USA",
    "place_id": "ChIJHREPbUle7IgRElIuBJeDdoM",
    "maps_url": "https://maps.google.com/?cid=9472903550853861906"
  },
  {
    "name": "Massey Services Pest Control",
    "rating": 4.1,
    "reviews": 88,
    "phone": "(850) 222-2508",
    "website": "https://www.masseyservices.com/service-location/tallahassee-pest-control/?utm_source=googlemybusiness&utm_medium=search&utm_content=Tallahassee52&utm_campaign=masseylocalsearch",
    "address": "3209 W Tharpe St, Tallahassee, FL 32303, USA",
    "place_id": "ChIJ55r5_Hf07IgRklkXJh0pJXU",
    "maps_url": "https://maps.google.com/?cid=8441198281745717650"
  },
  {
    "name": "Cook's Pest Control",
    "rating": 4.3,
    "reviews": 16,
    "phone": "(850) 391-1583",
    "website": "https://www.cookspest.com/branches/tallahassee",
    "address": "1531 Commonwealth Business Dr Apartment 103, Tallahassee, FL 32303, USA",
    "place_id": "ChIJUUdvmYRZ6WMRJvv37cRbC8Y",
    "maps_url": "https://maps.google.com/?cid=14270600745617718054"
  },
  {
    "name": "Pest Solutions of Tallahassee",
    "rating": 5,
    "reviews": 9,
    "phone": "(850) 296-2654",
    "website": "http://pestsolutionsoftallahassee.com/",
    "address": "3048 Adiron Way, Tallahassee, FL 32317, USA",
    "place_id": "ChIJDX0GA8Jd7IgRHPXTA3-_eoc",
    "maps_url": "https://maps.google.com/?cid=9762325694524945692"
  },
  {
    "name": "Nature's Finest",
    "rating": 4.3,
    "reviews": 20,
    "phone": "(850) 562-3960",
    "website": "http://naturesfinestpros.com/",
    "address": "3610 N Monroe St, Tallahassee, FL 32303, USA",
    "place_id": "ChIJo3lRWif07IgRcjG8fpUFl48",
    "maps_url": "https://maps.google.com/?cid=10346744808541532530"
  }
]